pi_lightsensor_webthing/__init__.py
pi_lightsensor_webthing/app.py
pi_lightsensor_webthing/lightsensor.py
pi_lightsensor_webthing/lightsensor_webthing.py
pi_lightsensor_webthing-0.2.22.dist-info/LICENSE
pi_lightsensor_webthing-0.2.22.dist-info/METADATA
pi_lightsensor_webthing-0.2.22.dist-info/WHEEL
pi_lightsensor_webthing-0.2.22.dist-info/entry_points.txt
pi_lightsensor_webthing-0.2.22.dist-info/top_level.txt
pi_lightsensor_webthing-0.2.22.dist-info/RECORD
