Metadata-Version: 2.1
Name: pi-lightsensor-webthing
Version: 0.2.22
Summary: A web connected digital light sensor measuring the intensity of ambient light on Raspberry Pi
Home-page: https://github.com/grro/pi_lightsensor_webthing
Author: Gregor Roth
Author-email: gregor.roth@web.de
License: MIT
Keywords: webthings,home automation,digital,light,sensor,ambient,light,BH1750
Platform: UNKNOWN
Classifier: Programming Language :: Python :: 3
Classifier: License :: OSI Approved :: Apache Software License
Classifier: Operating System :: OS Independent
Classifier: Development Status :: 3 - Alpha
Requires-Dist: webthing (>=0.15.0)
Requires-Dist: RPi.GPIO
Requires-Dist: adafruit-circuitpython-bh1750 (>=1.0.6)
